sns_toolbox/__init__.py
sns_toolbox/backends.py
sns_toolbox/color_utilities.py
sns_toolbox/compilers.py
sns_toolbox/connections.py
sns_toolbox/networks.py
sns_toolbox/neurons.py
sns_toolbox/plot_utilities.py
sns_toolbox/renderer.py
sns_toolbox/storage_utilities.py
sns_toolbox/design/__init__.py
sns_toolbox/design/connections.py
sns_toolbox/design/design_utilities.py
sns_toolbox/design/networks.py
sns_toolbox/design/neurons.py
sns_toolbox/simulate/__init__.py
sns_toolbox/simulate/backends.py
sns_toolbox/simulate/simulate_utilities.py
sns_toolbox-1.5.2.dist-info/LICENSE
sns_toolbox-1.5.2.dist-info/METADATA
sns_toolbox-1.5.2.dist-info/WHEEL
sns_toolbox-1.5.2.dist-info/top_level.txt
sns_toolbox-1.5.2.dist-info/RECORD
