Metadata-Version: 2.1
Name: sns-toolbox
Version: 1.5.2
Summary: Tools for designing Synthetic Nervous Systems, and simulating them on various software/hardware backends
Home-page: https://github.com/wnourse05/SNS-Toolbox
Author: William Nourse
Author-email: nourse@case.edu
License: Apache v2.0
Platform: UNKNOWN
Classifier: Development Status :: 3 - Alpha
Classifier: Environment :: GPU
Classifier: Intended Audience :: Science/Research
Classifier: License :: OSI Approved :: Apache Software License
Classifier: Natural Language :: English
Classifier: Operating System :: POSIX :: Linux
Classifier: Programming Language :: Python :: 3.5
Classifier: Programming Language :: Python :: 3.6
Classifier: Programming Language :: Python :: 3.7
Classifier: Programming Language :: Python :: 3.8
Classifier: Programming Language :: Python :: 3.9
Classifier: Programming Language :: Python :: 3.10
Classifier: Programming Language :: Python :: 3.11
Classifier: Topic :: Scientific/Engineering :: Artificial Intelligence
Requires-Python: >=3.5
Requires-Dist: graphviz
Requires-Dist: numpy (>=1.17)
Requires-Dist: torch
